iransms/__init__.py
iransms/config.py
iransms/sms_sender.py
iransms/providers/__init__.py
iransms/providers/dnspanel.py
iransms/providers/ippanel.py
iransms/providers/kavenegar.py
iransms/providers/provider_base.py
tests/__init__.py
tests/test_providers.py
tests/test_sms_sender.py
iransms-0.1.1.dist-info/METADATA
iransms-0.1.1.dist-info/WHEEL
iransms-0.1.1.dist-info/top_level.txt
iransms-0.1.1.dist-info/RECORD
