Metadata-Version: 2.1
Name: iransms
Version: 0.1.1
Summary: A Python package to send SMS via multiple Iranian providers
Home-page: https://github.com/navidsalehi/iransms
Author: Navid Salehi pour
Author-email: navid.lord@gmail.com
Classifier: Programming Language :: Python :: 3
Classifier: License :: OSI Approved :: MIT License
Classifier: Operating System :: OS Independent
Requires-Python: >=3.6
Requires-Dist: requests>=2.26.0
Requires-Dist: django>=3.2
